stable_diffusion_videos/__init__.py
stable_diffusion_videos/app.py
stable_diffusion_videos/flax_stable_diffusion_pipeline.py
stable_diffusion_videos/image_generation.py
stable_diffusion_videos/stable_diffusion_pipeline.py
stable_diffusion_videos/upsampling.py
stable_diffusion_videos/utils.py
stable_diffusion_videos-0.9.2.dist-info/licenses/LICENSE
stable_diffusion_videos-0.9.2.dist-info/METADATA
stable_diffusion_videos-0.9.2.dist-info/WHEEL
stable_diffusion_videos-0.9.2.dist-info/top_level.txt
stable_diffusion_videos-0.9.2.dist-info/RECORD
