Metadata-Version: 2.4
Name: stable_diffusion_videos
Version: 0.9.2
Summary: Create 🔥 videos with Stable Diffusion by exploring the latent space and morphing between text prompts.
Author-email: Nathan Raw <naterawdata@gmail.com>
License:                                  Apache License
Project-URL: Source, https://github.com/nateraw/stable-diffusion-videos
License-File: LICENSE
Requires-Dist: transformers>=4.21.0
Requires-Dist: diffusers
Requires-Dist: scipy
Requires-Dist: fire
Requires-Dist: gradio
Requires-Dist: librosa
Requires-Dist: av
Requires-Dist: realesrgan
Requires-Dist: protobuf==3.20.*
Requires-Dist: fsspec>=2023.4.0
Dynamic: license-file
